CHANGES
COPYING
INSTALL
MANIFEST.in
README
setup.py
foaflib/__init__.py
foaflib.egg-info/PKG-INFO
foaflib.egg-info/SOURCES.txt
foaflib.egg-info/dependency_links.txt
foaflib.egg-info/requires.txt
foaflib.egg-info/top_level.txt
foaflib/classes/__init__.py
foaflib/classes/agent.py
foaflib/classes/onlineaccount.py
foaflib/classes/person.py
foaflib/helpers/__init__.py
foaflib/helpers/basehelper.py
foaflib/helpers/blog.py
foaflib/helpers/delicious.py
foaflib/helpers/identica.py
foaflib/helpers/twitter_.py
foaflib/utils/__init__.py
foaflib/utils/activitystream.py
foaflib/utils/activitystreamevent.py
foaflib/utils/basicscutter.py
foaflib/utils/basicscutter.pyc
foaflib/utils/filestoragescutter.py