Metadata-Version: 1.0
Name: foaflib
Version: 0.2
Summary: Python library for working with FOAF data
Home-page: http://code.google.com/p/foaflib/
Author: Luke Maurits
Author-email: luke@maurits.id.au
License: UNKNOWN
Platform: UNKNOWN
